hexbot/__init__.py
hexbot-0.0.1.dist-info/METADATA
hexbot-0.0.1.dist-info/WHEEL
hexbot-0.0.1.dist-info/top_level.txt
hexbot-0.0.1.dist-info/RECORD
